prixCarburantGloirdClient/prixCarburantGloirdClient.py
Prix_Carburant_FR_Gloird_Client-0.0.4.dist-info/METADATA
Prix_Carburant_FR_Gloird_Client-0.0.4.dist-info/WHEEL
Prix_Carburant_FR_Gloird_Client-0.0.4.dist-info/entry_points.txt
Prix_Carburant_FR_Gloird_Client-0.0.4.dist-info/top_level.txt
Prix_Carburant_FR_Gloird_Client-0.0.4.dist-info/RECORD
