Metadata-Version: 2.1
Name: Prix-Carburant-FR-Gloird-Client
Version: 0.0.4
Summary: StationEssence client by Gloird
Home-page: https://github.com/Gloird/essence
Author: Maxime Wantiez, Yann RITTER, Nicolas <Gloird> DUPUIS
Author-email: gloird@gmail.com
License: MIT
Platform: UNKNOWN
